landerslabutils/__init__.py
landerslabutils/landerslabutils.py
landerslabutils-0.0.3.dist-info/METADATA
landerslabutils-0.0.3.dist-info/WHEEL
landerslabutils-0.0.3.dist-info/top_level.txt
landerslabutils-0.0.3.dist-info/RECORD
