Metadata-Version: 2.1
Name: landerslabutils
Version: 0.0.3
Summary: Landers Lab utilities for ALS compute project
Home-page: https://github.com/albertobrusati/LandersLabUtils
Author: alberto brusati
Author-email: a.brusati@auxologico.it
License: MIT
Keywords: bioinformatic,molecular data,hail,genetics
Classifier: Development Status :: 3 - Alpha
Classifier: Intended Audience :: Developers
Classifier: Topic :: Software Development :: Build Tools
Classifier: License :: OSI Approved :: MIT License
Classifier: Programming Language :: Python :: 3.8
Classifier: Programming Language :: Python :: 3.9
Classifier: Programming Language :: Python :: 3.10
Classifier: Programming Language :: Python :: 3.11
Requires-Dist: hail
Requires-Dist: pandas
Requires-Dist: bokeh
